README.rst
setup.py
barbot/__init__.py
barbot/barbot.py
barbot/constants.py
barbot/decorators.py
barbot/utils.py
barbot.egg-info/PKG-INFO
barbot.egg-info/SOURCES.txt
barbot.egg-info/dependency_links.txt
barbot.egg-info/requires.txt
barbot.egg-info/top_level.txt