Metadata-Version: 1.1
Name: barbot
Version: 1.2.2
Summary: Create your bot for barbars.ru.
Home-page: https://github.com/pyvim/barbot
Author: Vitalii Maslov
Author-email: me@pyvim.com
License: MIT
Download-URL: https://github.com/pyvim/barbot/tarball/master
Keywords: barbars.ru,bot,game
Platform: UNKNOWN
Classifier: Environment :: Web Environment
Classifier: Intended Audience :: Developers
Classifier: Programming Language :: Python
